nonebot_plugin_mrhelper/__init__.py
nonebot_plugin_mrhelper/callapi.py
nonebot_plugin_mrhelper/model.py
nonebot_plugin_mrhelper/sqlite.py
nonebot_plugin_mrhelper-1.0.dist-info/LICENSE
nonebot_plugin_mrhelper-1.0.dist-info/METADATA
nonebot_plugin_mrhelper-1.0.dist-info/WHEEL
nonebot_plugin_mrhelper-1.0.dist-info/top_level.txt
nonebot_plugin_mrhelper-1.0.dist-info/RECORD
